spcm/__init__.py
spcm/_version.py
spcm/classes_aba.py
spcm/classes_block_average.py
spcm/classes_block_statistics.py
spcm/classes_boxcar.py
spcm/classes_card.py
spcm/classes_card_stack.py
spcm/classes_channels.py
spcm/classes_clock.py
spcm/classes_data_transfer.py
spcm/classes_dds.py
spcm/classes_dds_command_list.py
spcm/classes_dds_command_queue.py
spcm/classes_device.py
spcm/classes_error_exception.py
spcm/classes_functionality.py
spcm/classes_gated.py
spcm/classes_multi.py
spcm/classes_multi_purpose_ios.py
spcm/classes_netbox.py
spcm/classes_pulse_generators.py
spcm/classes_scapp.py
spcm/classes_sequence.py
spcm/classes_sync.py
spcm/classes_synchronous_digital_ios.py
spcm/classes_time_stamp.py
spcm/classes_trigger.py
spcm/classes_unit_conversion.py
spcm-1.12.0.dist-info/licenses/LICENSE
spcm-1.12.0.dist-info/METADATA
spcm-1.12.0.dist-info/WHEEL
spcm-1.12.0.dist-info/top_level.txt
spcm-1.12.0.dist-info/RECORD
