Metadata-Version: 2.4
Name: spcm
Version: 1.12.0
Summary: Package for Spectrum Instrumentation GmbH cards
Author-email: Spectrum Instrumentation GmbH <info@spec.de>
Project-URL: Homepage, https://spectrum-instrumentation.com/
Project-URL: API, https://spectruminstrumentation.github.io/spcm/spcm.html
Project-URL: Repository, https://github.com/SpectrumInstrumentation/spcm
Project-URL: Examples, https://github.com/SpectrumInstrumentation/spcm/tree/master/src/examples
Project-URL: Knowledge Base, https://spectrum-instrumentation.com/support/knowledgebase/index.php
Classifier: Development Status :: 4 - Beta
Classifier: Intended Audience :: Developers
Classifier: Intended Audience :: Science/Research
Classifier: License :: OSI Approved :: MIT License
Classifier: Natural Language :: English
Classifier: Operating System :: POSIX :: Linux
Classifier: Operating System :: Microsoft :: Windows
Classifier: Programming Language :: Python
Classifier: Programming Language :: Python :: 3.9
Classifier: Programming Language :: Python :: 3.10
Classifier: Programming Language :: Python :: 3.11
Classifier: Programming Language :: Python :: 3.12
Classifier: Programming Language :: Python :: 3.13
Classifier: Topic :: Scientific/Engineering
Classifier: Topic :: System :: Hardware
Requires-Python: >=3.9
License-File: LICENSE
Requires-Dist: spcm_core>=1.0.0
Requires-Dist: numpy>=1.23
Requires-Dist: pint>=0.24
Provides-Extra: cuda
Requires-Dist: cupy>=13.2.0; extra == "cuda"
Requires-Dist: cuda-python>=12.5.0; extra == "cuda"
Requires-Dist: h5py>=3.10.0; extra == "cuda"
Dynamic: license-file
